cachepot/__init__.py
cachepot/_version.py
cachepot/expire.py
cachepot/py.typed
cachepot/backend/__init__.py
cachepot/backend/filesystem.py
cachepot/backend/redis.py
cachepot/backend/sqlite.py
cachepot/serializer/__init__.py
cachepot/serializer/json.py
cachepot/serializer/pickle.py
cachepot/serializer/str.py
cachepot/store/__init__.py
example/__init__.py
tests/__init__.py
tests/test_expire.py
tests/test_store.py
tests/backend/__init__.py
tests/backend/test_filesystem.py
tests/backend/test_redis.py
tests/backend/test_sqlite.py
tests/serializer/__init__.py
tests/serializer/test_json.py
tests/serializer/test_pickle.py
tests/serializer/test_str.py
cachepot-0.4.0.dist-info/LICENSE
cachepot-0.4.0.dist-info/METADATA
cachepot-0.4.0.dist-info/WHEEL
cachepot-0.4.0.dist-info/top_level.txt
cachepot-0.4.0.dist-info/RECORD
